Metadata-Version: 2.1
Name: oneNeuron-pypi-martuzaiu
Version: 0.0.2
Summary: A simple perceptron program
Home-page: https://github.com/martuzaiu/oneNeuron_pypi
Author: martuzaiu
Author-email: martuza.cse@gmail.com
License: UNKNOWN
Project-URL: Bug Tracker, https://github.com/martuzaiu/oneNeuron_pypi/issues
Platform: UNKNOWN
Classifier: Programming Language :: Python :: 3
Classifier: License :: OSI Approved :: MIT License
Classifier: Operating System :: OS Independent
Requires-Python: >=3.7
License-File: LICENSE
Requires-Dist: numpy
Requires-Dist: tqdm
